fpocketr/__init__.py
fpocketr/__main__.py
fpocketr/analyze.py
fpocketr/figures.py
fpocketr/make3D.py
fpocketr/pocket.py
fpocketr/util.py
fpocketr/rnavigate/__init__.py
fpocketr/rnavigate/data_loading.py
fpocketr/rnavigate/helper_functions.py
fpocketr/rnavigate/plotting_functions.py
fpocketr/rnavigate/rnavigate.py
fpocketr/rnavigate/styles.py
fpocketr/rnavigate/data/__init__.py
fpocketr/rnavigate/data/alignments.py
fpocketr/rnavigate/data/annotation.py
fpocketr/rnavigate/data/colors.py
fpocketr/rnavigate/data/data.py
fpocketr/rnavigate/data/interactions.py
fpocketr/rnavigate/data/pdb.py
fpocketr/rnavigate/data/profile.py
fpocketr/rnavigate/data/secondary_structure.py
fpocketr/rnavigate/plots/__init__.py
fpocketr/rnavigate/plots/plots.py
fpocketr/rnavigate/plots/ss.py
fpocketr/rnavigate/plots/functions/__init__.py
fpocketr/rnavigate/plots/functions/functions.py
fpocketr/rnavigate/plots/functions/ss.py
fpocketr-1.2.1.dist-info/LICENSE.txt
fpocketr-1.2.1.dist-info/METADATA
fpocketr-1.2.1.dist-info/WHEEL
fpocketr-1.2.1.dist-info/top_level.txt
fpocketr-1.2.1.dist-info/RECORD
