Metadata-Version: 2.2
Name: fpocketr
Version: 1.2.1
Summary: Find, characterize, and visualize drug-like pockets in RNA structures.
Author-email: "Seth D. Veenbaas" <sdveenbaas@gmail.com>
License: MIT License
Project-URL: Homepage, https://github.com/Weeks-UNC/fpocketR
Project-URL: Issues, https://github.com/Weeks-UNC/fpocketR/issues
Classifier: Programming Language :: Python :: 3
Classifier: Operating System :: OS Independent
Requires-Python: >=3.11
License-File: LICENSE.txt
Requires-Dist: fpocket==4.0.3
Requires-Dist: pymol-open-source==2.5.0
Requires-Dist: prody==2.4.0
Requires-Dist: pandas==2.2.1
Requires-Dist: rdkit==2023.09.6
Requires-Dist: seaborn==0.13.2
Requires-Dist: trimesh==4.2.0
